neuralprocesses/__init__.py
neuralprocesses/_version.py
neuralprocesses/aggregate.py
neuralprocesses/augment.py
neuralprocesses/chain.py
neuralprocesses/coding.py
neuralprocesses/datadims.py
neuralprocesses/disc.py
neuralprocesses/likelihood.py
neuralprocesses/mask.py
neuralprocesses/materialise.py
neuralprocesses/numdata.py
neuralprocesses/parallel.py
neuralprocesses/util.py
neuralprocesses/architectures/__init__.py
neuralprocesses/architectures/agnp.py
neuralprocesses/architectures/climate.py
neuralprocesses/architectures/convgnp.py
neuralprocesses/architectures/fullconvgnp.py
neuralprocesses/architectures/gnp.py
neuralprocesses/architectures/util.py
neuralprocesses/coders/__init__.py
neuralprocesses/coders/aggregate.py
neuralprocesses/coders/attention.py
neuralprocesses/coders/augment.py
neuralprocesses/coders/copy.py
neuralprocesses/coders/deepset.py
neuralprocesses/coders/densecov.py
neuralprocesses/coders/functional.py
neuralprocesses/coders/fuse.py
neuralprocesses/coders/inputs.py
neuralprocesses/coders/mapdiag.py
neuralprocesses/coders/nn.py
neuralprocesses/coders/shaping.py
neuralprocesses/coders/setconv/__init__.py
neuralprocesses/coders/setconv/density.py
neuralprocesses/coders/setconv/identity.py
neuralprocesses/coders/setconv/setconv.py
neuralprocesses/data/__init__.py
neuralprocesses/data/antarctica.py
neuralprocesses/data/batch.py
neuralprocesses/data/bimodal.py
neuralprocesses/data/data.py
neuralprocesses/data/eeg.py
neuralprocesses/data/gp.py
neuralprocesses/data/mixgp.py
neuralprocesses/data/mixture.py
neuralprocesses/data/predefined.py
neuralprocesses/data/predprey.py
neuralprocesses/data/sawtooth.py
neuralprocesses/data/temperature.py
neuralprocesses/data/util.py
neuralprocesses/dist/__init__.py
neuralprocesses/dist/beta.py
neuralprocesses/dist/dirac.py
neuralprocesses/dist/dist.py
neuralprocesses/dist/gamma.py
neuralprocesses/dist/geom.py
neuralprocesses/dist/normal.py
neuralprocesses/dist/spikeslab.py
neuralprocesses/dist/transformed.py
neuralprocesses-0.2.7.dist-info/METADATA
neuralprocesses-0.2.7.dist-info/WHEEL
neuralprocesses-0.2.7.dist-info/licenses/LICENCE.txt
neuralprocesses-0.2.7.dist-info/RECORD
