Metadata-Version: 2.4
Name: NeuralProcesses
Version: 0.2.7
Summary: A framework for composing Neural Processes in Python
Project-URL: repository, https://github.com/wesselb/neuralprocesses
Author-email: Wessel Bruinsma <wessel.p.bruinsma@gmail.com>
License: MIT
License-File: LICENCE.txt
Requires-Python: >=3.8
Requires-Dist: backends-matrix>=1.2.10
Requires-Dist: backends>=1.6.2
Requires-Dist: numpy>=1.16
Requires-Dist: plum-dispatch>=2.3.0
Requires-Dist: stheno>=1.4.2
Requires-Dist: wbml>=0.3.18
Provides-Extra: dev
Requires-Dist: black==23.7.0; extra == 'dev'
Requires-Dist: build; extra == 'dev'
Requires-Dist: coveralls; extra == 'dev'
Requires-Dist: ghp-import; extra == 'dev'
Requires-Dist: ipython; extra == 'dev'
Requires-Dist: jupyter-book; extra == 'dev'
Requires-Dist: mypy; extra == 'dev'
Requires-Dist: numpy; extra == 'dev'
Requires-Dist: pre-commit; extra == 'dev'
Requires-Dist: pyright; extra == 'dev'
Requires-Dist: pytest-cov; extra == 'dev'
Requires-Dist: pytest>=6; extra == 'dev'
Requires-Dist: tensorflow; extra == 'dev'
Requires-Dist: tensorflow-probability[tf]; extra == 'dev'
Requires-Dist: torch; extra == 'dev'
Requires-Dist: tox; extra == 'dev'
Requires-Dist: wheel; extra == 'dev'
